kvmm/__init__.py
kvmm/model_registry.py
kvmm/version.py
kvmm/layers/__init__.py
kvmm/layers/affine.py
kvmm/layers/class_attention.py
kvmm/layers/class_dist_token.py
kvmm/layers/efficient_multi_head_self_attention.py
kvmm/layers/global_response_norm.py
kvmm/layers/image_normalization.py
kvmm/layers/images_to_patches.py
kvmm/layers/layer_scale.py
kvmm/layers/multi_head_self_attention.py
kvmm/layers/patches_to_images.py
kvmm/layers/pos_embedding.py
kvmm/layers/std_conv2d.py
kvmm/layers/stochastic_depth.py
kvmm/layers/talking_head_attention.py
kvmm/layers/window_attention.py
kvmm/layers/window_partition.py
kvmm/layers/window_reverse.py
kvmm/models/__init__.py
kvmm/models/cait/__init__.py
kvmm/models/cait/cait_model.py
kvmm/models/cait/config.py
kvmm/models/cait/convert_cait_torch_to_keras.py
kvmm/models/clip/__init__.py
kvmm/models/clip/clip_image_processor.py
kvmm/models/clip/clip_layers.py
kvmm/models/clip/clip_model.py
kvmm/models/clip/clip_processor.py
kvmm/models/clip/clip_tokenizer.py
kvmm/models/clip/config.py
kvmm/models/clip/convert_clip_torch_to_keras.py
kvmm/models/convmixer/__init__.py
kvmm/models/convmixer/config.py
kvmm/models/convmixer/convert_convmixer_torch_to_keras.py
kvmm/models/convmixer/convmixer_model.py
kvmm/models/convnext/__init__.py
kvmm/models/convnext/config.py
kvmm/models/convnext/convert_convnext_torch_to_keras.py
kvmm/models/convnext/convnext_model.py
kvmm/models/convnextv2/__init__.py
kvmm/models/convnextv2/config.py
kvmm/models/convnextv2/convert_convnextv2_torch_to_keras.py
kvmm/models/convnextv2/convnextv2_model.py
kvmm/models/deit/__init__.py
kvmm/models/deit/config.py
kvmm/models/deit/convert_deit_torch_to_keras.py
kvmm/models/deit/deit_model.py
kvmm/models/densenet/__init__.py
kvmm/models/densenet/config.py
kvmm/models/densenet/convert_densenet_torch_to_keras.py
kvmm/models/densenet/densenet_model.py
kvmm/models/efficientnet/__init__.py
kvmm/models/efficientnet/config.py
kvmm-0.1.8.dist-info/licenses/LICENSE
kvmm-0.1.8.dist-info/METADATA
kvmm-0.1.8.dist-info/WHEEL
kvmm-0.1.8.dist-info/top_level.txt
kvmm-0.1.8.dist-info/RECORD
