Metadata-Version: 2.4
Name: kvmm
Version: 0.1.8
Summary: Pretrained keras 3 vision models
Author-email: Gitesh Chawda <gitesh.ch.0912@gmail.com>
License: Apache License 2.0
Project-URL: homepage, https://github.com/IMvision12/keras-vision-models
Project-URL: documentation, https://github.com/IMvision12/keras-vision-models
Project-URL: repository, https://github.com/IMvision12/keras-vision-models.git
Keywords: machine-learning,jax,computer-vision,neural-networks,tensorflow,torch,deep-learning,keras,imagenet,pretrained-weights,convolutional-neural-networks,transfer-learning,python-ml,data-science,ai-research,vision-transformer,image-classification,model-training,pytorch
Classifier: Intended Audience :: Education
Classifier: Intended Audience :: Science/Research
Classifier: License :: OSI Approved :: Apache Software License
Classifier: Programming Language :: Python :: 3.8
Classifier: Programming Language :: Python :: 3.9
Classifier: Programming Language :: Python :: 3.10
Classifier: Programming Language :: Python :: 3.11
Classifier: Programming Language :: Python :: 3.12
Classifier: Topic :: Scientific/Engineering
Classifier: Topic :: Scientific/Engineering :: Artificial Intelligence
Classifier: Topic :: Software Development
Classifier: Topic :: Software Development :: Libraries
Classifier: Topic :: Software Development :: Libraries :: Python Modules
Requires-Python: >=3.11
License-File: LICENSE
Requires-Dist: keras
Dynamic: license-file
